CHANGES.txt
LICENSE.txt
MANIFEST.in
README.rst
setup.py
gentool.egg-info/PKG-INFO
gentool.egg-info/SOURCES.txt
gentool.egg-info/dependency_links.txt
gentool.egg-info/entry_points.txt
gentool.egg-info/requires.txt
gentool.egg-info/top_level.txt
src/__init__.py
src/cli.py
src/misc.py
src/scripts.py
src/utils/__init__.py
src/utils/chmod.py
src/utils/decorators.py