Metadata-Version: 1.1
Name: gentool
Version: 1.0.1
Summary: 
